mxfold2/__init__.py
mxfold2/__main__.py
mxfold2/bpseq2fa.py
mxfold2/compbpseq.py
mxfold2/dataset.py
mxfold2/fold/embedding.py
mxfold2/fold/fold.py
mxfold2/fold/layers.py
mxfold2/fold/mix.py
mxfold2/fold/rnafold.py
mxfold2/fold/transformer.py
mxfold2/fold/zuker.py
mxfold2/loss.py
mxfold2/models/TrainSetAB.conf
mxfold2/models/TrainSetAB.pth
mxfold2/param_turner2004.py
mxfold2/predict.py
mxfold2/show_param.py
mxfold2/src/CMakeLists.txt
mxfold2/src/fold/fold.cpp
mxfold2/src/fold/fold.h
mxfold2/src/fold/nussinov.cpp
mxfold2/src/fold/nussinov.h
mxfold2/src/fold/trimatrix.h
mxfold2/src/fold/zuker.cpp
mxfold2/src/fold/zuker.h
mxfold2/src/interface.cpp
mxfold2/src/param/bpscore.cpp
mxfold2/src/param/bpscore.h
mxfold2/src/param/mix.cpp
mxfold2/src/param/mix.h
mxfold2/src/param/positional.cpp
mxfold2/src/param/positional.h
mxfold2/src/param/turner.cpp
mxfold2/src/param/turner.h
mxfold2/src/param/util.h
mxfold2/src/pybind11/.appveyor.yml
mxfold2/src/pybind11/.cmake-format.yaml
mxfold2/src/pybind11/.git
mxfold2/src/pybind11/.github/workflows/ci.yml
mxfold2/src/pybind11/.github/workflows/configure.yml
mxfold2/src/pybind11/.github/workflows/format.yml
mxfold2/src/pybind11/.gitignore
mxfold2/src/pybind11/.gitmodules
mxfold2/src/pybind11/.pre-commit-config.yaml
mxfold2/src/pybind11/.readthedocs.yml
mxfold2/src/pybind11/CMakeLists.txt
mxfold2/src/pybind11/CONTRIBUTING.md
mxfold2/src/pybind11/ISSUE_TEMPLATE.md
mxfold2/src/pybind11/LICENSE
mxfold2/src/pybind11/MANIFEST.in
mxfold2/src/pybind11/README.md
mxfold2/src/pybind11/docs/Doxyfile
mxfold2/src/pybind11/docs/Makefile
mxfold2/src/pybind11/docs/_static/theme_overrides.css
mxfold2/src/pybind11/docs/advanced/cast/chrono.rst
mxfold2/src/pybind11/docs/advanced/cast/custom.rst
mxfold2/src/pybind11/docs/advanced/cast/eigen.rst
mxfold2/src/pybind11/docs/advanced/cast/functional.rst
mxfold2/src/pybind11/docs/advanced/cast/index.rst
mxfold2/src/pybind11/docs/advanced/cast/overview.rst
mxfold2/src/pybind11/docs/advanced/cast/stl.rst
mxfold2-0.1.1.dist-info/entry_points.txt
mxfold2-0.1.1.dist-info/LICENSE
mxfold2-0.1.1.dist-info/WHEEL
mxfold2-0.1.1.dist-info/METADATA
mxfold2-0.1.1.dist-info/RECORD
