Metadata-Version: 2.1
Name: mxfold2
Version: 0.1.1
Summary: RNA secondary structure prediction using deep neural networks with thermodynamic integrations
Home-page: https://github.com/keio-bioinformatics/mxfold2
License: MIT
Author: Kengo Sato
Author-email: satoken@bio.keio.ac.jp
Requires-Python: >=3.7,<4.0
Classifier: License :: OSI Approved :: MIT License
Classifier: Programming Language :: Python :: 3
Classifier: Programming Language :: Python :: 3.7
Classifier: Programming Language :: Python :: 3.8
Requires-Dist: numpy (>=1.18,<2.0)
Requires-Dist: torch (>=1.4,<2.0)
Requires-Dist: torchvision (>=0,<1)
Requires-Dist: tqdm (>=4.40,<5.0)
Requires-Dist: wheel (>=0.35.1,<0.36.0)
Project-URL: Repository, https://github.com/keio-bioinformatics/mxfold2
